Workbook

Sheet Dashboard
A1: 💰 FUND PAYMENT & SPENDING TRACKER
A3: FUND SETUP
A4: Total Fund Amount | B4: Total Received | C4: Total Spent | D4: Balance Remaining | E4: % Received | F4: % Spent | G4: % Balance
A5: =Payments!B3 -> 1000000 | B5: =SUM(Payments!E5:E20) -> 1000000 | C5: =SUM(Spendings!E4:E53) -> 311500 | D5: =B5-C5 -> 688500 | E5: =IFERROR(B5/A5,"-") -> 1 | F5: =IFERROR(C5/A5,"-") -> 0.3115 | G5: =IFERROR(D5/A5,"-") -> 0.6885
A8: TRANCHE SUMMARY
A9: Tranche # | B9: Date Received | C9: Description | D9: % of Fund | E9: Amount Received | F9: Amount Spent | G9: Unspent Balance | H9: Status
A10: =IF(Payments!A6="","",Payments!A6) -> 1 | B10: =IF(Payments!B6="","",Payments!B6) -> 45667 | C10: =IF(Payments!C6="","",Payments!C6) -> First Tranche – 70% advance | D10: =IFERROR(Payments!D6/Payments!$B$3,"") -> 7e-07 | E10: =IF(Payments!E6="","",Payments!E6) -> 700000 | F10: =IFERROR(SUMIF(Spendings!B:B,Payments!A6,Spendings!E:E),"") -> 0 | G10: =IFERROR(E10-F10,"") -> 700000 | H10: =IF(E10="","",IF(G10<=0,"⚠ Over Budget",IF(G10=0,"✔ Fully Spent","✅ In Budget"))) -> ✅ In Budget
A11: =IF(Payments!A7="","",Payments!A7) -> 2 | B11: =IF(Payments!B7="","",Payments!B7) -> 45823 | C11: =IF(Payments!C7="","",Payments!C7) -> Second Tranche – 30% final | D11: =IFERROR(Payments!D7/Payments!$B$3,"") -> 3e-07 | E11: =IF(Payments!E7="","",Payments!E7) -> 300000 | F11: =IFERROR(SUMIF(Spendings!B:B,Payments!A7,Spendings!E:E),"") -> 0 | G11: =IFERROR(E11-F11,"") -> 300000 | H11: =IF(E11="","",IF(G11<=0,"⚠ Over Budget",IF(G11=0,"✔ Fully Spent","✅ In Budget"))) -> ✅ In Budget
A12: =IF(Payments!A8="","",Payments!A8) | B12: =IF(Payments!B8="","",Payments!B8) | C12: =IF(Payments!C8="","",Payments!C8) | D12: =IFERROR(Payments!D8/Payments!$B$3,"") -> 0 | E12: =IF(Payments!E8="","",Payments!E8) | F12: =IFERROR(SUMIF(Spendings!B:B,Payments!A8,Spendings!E:E),"") -> 0 | G12: =IFERROR(E12-F12,"") | H12: =IF(E12="","",IF(G12<=0,"⚠ Over Budget",IF(G12=0,"✔ Fully Spent","✅ In Budget")))
A13: =IF(Payments!A9="","",Payments!A9) | B13: =IF(Payments!B9="","",Payments!B9) | C13: =IF(Payments!C9="","",Payments!C9) | D13: =IFERROR(Payments!D9/Payments!$B$3,"") -> 0 | E13: =IF(Payments!E9="","",Payments!E9) | F13: =IFERROR(SUMIF(Spendings!B:B,Payments!A9,Spendings!E:E),"") -> 0 | G13: =IFERROR(E13-F13,"") | H13: =IF(E13="","",IF(G13<=0,"⚠ Over Budget",IF(G13=0,"✔ Fully Spent","✅ In Budget")))
A14: =IF(Payments!A10="","",Payments!A10) | B14: =IF(Payments!B10="","",Payments!B10) | C14: =IF(Payments!C10="","",Payments!C10) | D14: =IFERROR(Payments!D10/Payments!$B$3,"") -> 0 | E14: =IF(Payments!E10="","",Payments!E10) | F14: =IFERROR(SUMIF(Spendings!B:B,Payments!A10,Spendings!E:E),"") -> 0 | G14: =IFERROR(E14-F14,"") | H14: =IF(E14="","",IF(G14<=0,"⚠ Over Budget",IF(G14=0,"✔ Fully Spent","✅ In Budget")))
A15: =IF(Payments!A11="","",Payments!A11) | B15: =IF(Payments!B11="","",Payments!B11) | C15: =IF(Payments!C11="","",Payments!C11) | D15: =IFERROR(Payments!D11/Payments!$B$3,"") -> 0 | E15: =IF(Payments!E11="","",Payments!E11) | F15: =IFERROR(SUMIF(Spendings!B:B,Payments!A11,Spendings!E:E),"") -> 0 | G15: =IFERROR(E15-F15,"") | H15: =IF(E15="","",IF(G15<=0,"⚠ Over Budget",IF(G15=0,"✔ Fully Spent","✅ In Budget")))
A16: =IF(Payments!A12="","",Payments!A12) | B16: =IF(Payments!B12="","",Payments!B12) | C16: =IF(Payments!C12="","",Payments!C12) | D16: =IFERROR(Payments!D12/Payments!$B$3,"") -> 0 | E16: =IF(Payments!E12="","",Payments!E12) | F16: =IFERROR(SUMIF(Spendings!B:B,Payments!A12,Spendings!E:E),"") -> 0 | G16: =IFERROR(E16-F16,"") | H16: =IF(E16="","",IF(G16<=0,"⚠ Over Budget",IF(G16=0,"✔ Fully Spent","✅ In Budget")))
A17: =IF(Payments!A13="","",Payments!A13) | B17: =IF(Payments!B13="","",Payments!B13) | C17: =IF(Payments!C13="","",Payments!C13) | D17: =IFERROR(Payments!D13/Payments!$B$3,"") -> 0 | E17: =IF(Payments!E13="","",Payments!E13) | F17: =IFERROR(SUMIF(Spendings!B:B,Payments!A13,Spendings!E:E),"") -> 0 | G17: =IFERROR(E17-F17,"") | H17: =IF(E17="","",IF(G17<=0,"⚠ Over Budget",IF(G17=0,"✔ Fully Spent","✅ In Budget")))
A18: =IF(Payments!A14="","",Payments!A14) | B18: =IF(Payments!B14="","",Payments!B14) | C18: =IF(Payments!C14="","",Payments!C14) | D18: =IFERROR(Payments!D14/Payments!$B$3,"") -> 0 | E18: =IF(Payments!E14="","",Payments!E14) | F18: =IFERROR(SUMIF(Spendings!B:B,Payments!A14,Spendings!E:E),"") -> 0 | G18: =IFERROR(E18-F18,"") | H18: =IF(E18="","",IF(G18<=0,"⚠ Over Budget",IF(G18=0,"✔ Fully Spent","✅ In Budget")))
A19: =IF(Payments!A15="","",Payments!A15) | B19: =IF(Payments!B15="","",Payments!B15) | C19: =IF(Payments!C15="","",Payments!C15) | D19: =IFERROR(Payments!D15/Payments!$B$3,"") -> 0 | E19: =IF(Payments!E15="","",Payments!E15) | F19: =IFERROR(SUMIF(Spendings!B:B,Payments!A15,Spendings!E:E),"") -> 0 | G19: =IFERROR(E19-F19,"") | H19: =IF(E19="","",IF(G19<=0,"⚠ Over Budget",IF(G19=0,"✔ Fully Spent","✅ In Budget")))
A21: SPENDING BY CATEGORY
A22: Category | B22: Total Spent | C22: % of Total Spent
A23: Materials | B23: =SUM(Spendings!E:E) -> 623000 | C23: =IFERROR(B23/SUM(B23:B28),"-") -> 0.81491171
A24: Labour | B24: =IFERROR(SUMIF(Spendings!D:D,A24,Spendings!E:E),0) -> 85000 | C24: =IFERROR(B24/SUM(B23:B28),"-") -> 0.11118378
A25: Transport | B25: =IFERROR(SUMIF(Spendings!D:D,A25,Spendings!E:E),0) -> 33000 | C25: =IFERROR(B25/SUM(B23:B28),"-") -> 0.043165468
A26: Admin | B26: =IFERROR(SUMIF(Spendings!D:D,A26,Spendings!E:E),0) -> 3500 | C26: =IFERROR(B26/SUM(B23:B28),"-") -> 0.0045781557
A27: Utilities | B27: =IFERROR(SUMIF(Spendings!D:D,A27,Spendings!E:E),0) -> 8000 | C27: =IFERROR(B27/SUM(B23:B28),"-") -> 0.010464356
A28: Miscellaneous | B28: =IFERROR(SUMIF(Spendings!D:D,A28,Spendings!E:E),0) -> 12000 | C28: =IFERROR(B28/SUM(B23:B28),"-") -> 0.015696534
A29: TOTAL | B29: =SUM(B23:B28) -> 764500 | C29: =IFERROR(B29/SUM(B21:B26),"100%") -> 1.0268637

Sheet Payments
A1: PAYMENTS RECEIVED LOG
A3: Total Fund Amount: | B3: 1000000 | C3: ← Enter your total fund amount here
A5: Tranche # | B5: Date Received | C5: Description / Milestone | D5: Amount (% of Fund) | E5: Amount Received | F5: Cumulative Received | G5: Running Balance | H5: Notes
A6: 1 | B6: 45667 | C6: First Tranche – 70% advance | D6: 0.7 | E6: =IFERROR(IF(D6="","",D6*$B$3),"") -> 700000 | F6: =IFERROR(SUM($E$6:E6),"") -> 700000 | G6: =IFERROR($B$3-F6,"") -> 300000
A7: 2 | B7: 45823 | C7: Second Tranche – 30% final | D7: 0.3 | E7: =IFERROR(IF(D7="","",D7*$B$3),"") -> 300000 | F7: =IFERROR(SUM($E$6:E7),"") -> 1000000 | G7: =IFERROR($B$3-F7,"") -> 0
F8: =IFERROR(SUM($E$6:E8),"") -> 1000000 | G8: =IFERROR($B$3-F8,"") -> 0
F9: =IFERROR(SUM($E$6:E9),"") -> 1000000 | G9: =IFERROR($B$3-F9,"") -> 0
E10: =IFERROR(IF(D10="","",D10*$B$3),"") | F10: =IFERROR(SUM($E$6:E10),"") -> 1000000 | G10: =IFERROR($B$3-F10,"") -> 0
E11: =IFERROR(IF(D11="","",D11*$B$3),"") | F11: =IFERROR(SUM($E$6:E11),"") -> 1000000 | G11: =IFERROR($B$3-F11,"") -> 0
E12: =IFERROR(IF(D12="","",D12*$B$3),"") | F12: =IFERROR(SUM($E$6:E12),"") -> 1000000 | G12: =IFERROR($B$3-F12,"") -> 0
E13: =IFERROR(IF(D13="","",D13*$B$3),"") | F13: =IFERROR(SUM($E$6:E13),"") -> 1000000 | G13: =IFERROR($B$3-F13,"") -> 0
E14: =IFERROR(IF(D14="","",D14*$B$3),"") | F14: =IFERROR(SUM($E$6:E14),"") -> 1000000 | G14: =IFERROR($B$3-F14,"") -> 0
E15: =IFERROR(IF(D15="","",D15*$B$3),"") | F15: =IFERROR(SUM($E$6:E15),"") -> 1000000 | G15: =IFERROR($B$3-F15,"") -> 0
E16: =IFERROR(IF(D16="","",D16*$B$3),"") | F16: =IFERROR(SUM($E$6:E16),"") -> 1000000 | G16: =IFERROR($B$3-F16,"") -> 0
E17: =IFERROR(IF(D17="","",D17*$B$3),"") | F17: =IFERROR(SUM($E$6:E17),"") -> 1000000 | G17: =IFERROR($B$3-F17,"") -> 0
E18: =IFERROR(IF(D18="","",D18*$B$3),"") | F18: =IFERROR(SUM($E$6:E18),"") -> 1000000 | G18: =IFERROR($B$3-F18,"") -> 0
E19: =IFERROR(IF(D19="","",D19*$B$3),"") | F19: =IFERROR(SUM($E$6:E19),"") -> 1000000 | G19: =IFERROR($B$3-F19,"") -> 0
E20: =IFERROR(IF(D20="","",D20*$B$3),"") | F20: =IFERROR(SUM($E$6:E20),"") -> 1000000 | G20: =IFERROR($B$3-F20,"") -> 0
A21: Total | E21: =SUM(E6:E20) -> 1000000

Sheet Spendings
A1: SPENDINGS LOG
A3: Tranche # | B3: Date Spent | C3: Description | D3: Category | E3: Amount Spent | F3: Cumulative Spent | G3: Receipt/Ref # | H3: Notes
A4: 1 | B4: 45672 | C4: Site preparation | D4: Labour | E4: 25000 | F4: =IFERROR(SUM($E$4:E4),"") -> 25000
A5: 1 | B5: 45677 | C5: Raw materials – Phase 1 | D5: Materials | E5: 80000 | F5: =IFERROR(SUM($E$4:E5),"") -> 105000
A6: 1 | B6: 45693 | C6: Equipment transport | D6: Transport | E6: 15000 | F6: =IFERROR(SUM($E$4:E6),"") -> 120000
A7: 1 | B7: 45706 | C7: Office supplies | D7: Admin | E7: 3500 | F7: =IFERROR(SUM($E$4:E7),"") -> 123500
A8: 1 | B8: 45717 | C8: Electricity & Water | D8: Utilities | E8: 8000 | F8: =IFERROR(SUM($E$4:E8),"") -> 131500
A9: 1 | B9: 45738 | C9: Miscellaneous repairs | D9: Miscellaneous | E9: 12000 | F9: =IFERROR(SUM($E$4:E9),"") -> 143500
A10: 2 | B10: 45839 | C10: Labour – Phase 2 | D10: Labour | E10: 60000 | F10: =IFERROR(SUM($E$4:E10),"") -> 203500
A11: 2 | B11: 45848 | C11: Raw materials – Phase 2 | D11: Materials | E11: 90000 | F11: =IFERROR(SUM($E$4:E11),"") -> 293500
A12: 2 | B12: 45866 | C12: Logistics & delivery | D12: Transport | E12: 18000 | F12: =IFERROR(SUM($E$4:E12),"") -> 311500
F13: =IFERROR(SUM($E$4:E13),"") -> 311500
F14: =IFERROR(SUM($E$4:E14),"") -> 311500
F15: =IFERROR(SUM($E$4:E15),"") -> 311500
F16: =IFERROR(SUM($E$4:E16),"") -> 311500
F17: =IFERROR(SUM($E$4:E17),"") -> 311500
F18: =IFERROR(SUM($E$4:E18),"") -> 311500
F19: =IFERROR(SUM($E$4:E19),"") -> 311500
F20: =IFERROR(SUM($E$4:E20),"") -> 311500
F21: =IFERROR(SUM($E$4:E21),"") -> 311500
F22: =IFERROR(SUM($E$4:E22),"") -> 311500
F23: =IFERROR(SUM($E$4:E23),"") -> 311500
F24: =IFERROR(SUM($E$4:E24),"") -> 311500
... F53: =IFERROR(SUM($E$4:E53),"") -> 311500
A54: TOTAL | E54: =SUM(E4:E53) -> 311500

Sheet How To Use
A1: HOW TO USE THIS TRACKER
A3: Step | B3: Sheet | C3: Where | D3: Instructions
A4: STEP 1 – Set your Fund | B4: Payments | C4: B3 | D4: Enter your total approved fund amount in the yellow cell B3 on the Payments sheet.
A5: STEP 2 – Log each Tranche | B5: Payments | C5: Cols A–D & H | D5: Each time you receive a payment, add a row: Tranche #, Date, Description, % of Fund, and optional Notes. Amount, Cumulative & Balance auto-calculate.
A6: STEP 3 – Log each Spending | B6: Spendings | C6: Cols A–E & G–H | D6: For every expense, enter: Tranche # (links to which payment), Date, Description, Category (choose from dropdown once set), Amount. Cumulative total auto-updates.
A7: STEP 4 – View Dashboard | B7: Dashboard | C7: All | D7: Dashboard auto-summarises total received vs spent, per-tranche balance, and spending by category. No manual entry needed here.
A8: COLOUR GUIDE | B8: All Sheets | C8: — | D8: Blue text = cells you fill in. Black text = auto-calculated formulas. Yellow background = key totals/inputs. Green rows = payment entries. Orange rows = spending entries.
A9: CATEGORIES | B9: Spendings | C9: Col D | D9: Default categories: Materials, Labour, Transport, Admin, Utilities, Miscellaneous. Edit the Dashboard category list (A23:A28) to customise.
A10: ADDING ROWS | B10: Spendings | C10: — | D10: If you need more than 50 spending rows, copy the last row's formula structure downward. The cumulative column formula will adjust automatically.
